nameko_cachelib/__init__.py
nameko_cachelib/proxy.py
nameko_cachelib/rpc.py
nameko_cachelib-0.1.1.dist-info/LICENSE
nameko_cachelib-0.1.1.dist-info/WHEEL
nameko_cachelib-0.1.1.dist-info/METADATA
nameko_cachelib-0.1.1.dist-info/RECORD
